dist/tableviz-0.1.1-py3-none-any.whl
dist/tableviz-0.1.1.tar.gz
tableviz/__init__.py
tableviz/table_data.py
tableviz/utils.py
tableviz/components/__init__.py
tableviz/components/table.py
tableviz/templates/cell.html
tableviz/templates/index.html
tableviz/templates/table.html
test/test.py
test/test/index.html
test/test/images/image_0_avatar.jpg
test/test/images/image_1_avatar.jpg
test/test/images/image_2_avatar.jpg
test/test/images/image_3_avatar.jpg
test/test/images/image_4_avatar.jpg
test/test/images/image_5_avatar.jpg
test/test/images/image_6_avatar.jpg
test/test/images/image_7_avatar.jpg
tableviz-0.1.2.dist-info/LICENSE
tableviz-0.1.2.dist-info/METADATA
tableviz-0.1.2.dist-info/WHEEL
tableviz-0.1.2.dist-info/top_level.txt
tableviz-0.1.2.dist-info/RECORD
