Metadata-Version: 2.1
Name: tableviz
Version: 0.1.2
Summary: TableViz is a Python project that provides tools for organizing and visualizing tabular data in HTML format.
Author-email: Chuyang Zhao <chuyang.zhao@outlook.com>
License: MIT
Project-URL: Homepage, https://github.com/ZhaoChuyang/TableViz
Project-URL: Bug Tracker, https://github.com/ZhaoChuyang/TableViz/issues
Classifier: Programming Language :: Python :: 3
Classifier: Operating System :: OS Independent
Requires-Python: >=3.8
License-File: LICENSE
Requires-Dist: Jinja2
Requires-Dist: Pillow
Requires-Dist: numpy
